ativ03_ex/__init__.py
ativ03_ex/armazenamento.py
ativ03_ex/consulta.py
ativ03_ex/interacao.py
ativ03_ex-0.0.1.dist-info/LICENSE.txt
ativ03_ex-0.0.1.dist-info/METADATA
ativ03_ex-0.0.1.dist-info/WHEEL
ativ03_ex-0.0.1.dist-info/top_level.txt
ativ03_ex-0.0.1.dist-info/RECORD
