Metadata-Version: 2.1
Name: ativ03-ex
Version: 0.0.1
Summary: Pacote python criado para um exercicio
Home-page: https://github.com/LeKeu/Gerador---Nomes-de-RPG
Author: Leticia Keuffer Cavalleiro de Macedo
Author-email: lekeuffer@gmail.com
License: MIT License
Keywords: Pacote
Platform: UNKNOWN
License-File: LICENSE.txt
